{"sel":"CRO","copa":2022,"squad":[{"playerId":"dominik-livakovic","name":"Livaković","sel":"CRO","copa":2022,"positions":["GOL"],"number":1,"force":87,"legend":false},{"playerId":"ivo-grbic","name":"Grbić","sel":"CRO","copa":2022,"positions":["GOL"],"number":12,"force":74,"legend":false},{"playerId":"ivica-ivusic","name":"Ivušić","sel":"CRO","copa":2022,"positions":["GOL"],"number":23,"force":72,"legend":false},{"playerId":"josip-juranovic","name":"Juranović","sel":"CRO","copa":2022,"positions":["LD"],"number":22,"force":80,"legend":false},{"playerId":"borna-barisic","name":"Barišić","sel":"CRO","copa":2022,"positions":["LE","LD"],"number":3,"force":78,"legend":false},{"playerId":"dejan-lovren","name":"Lovren","sel":"CRO","copa":2022,"positions":["ZAG"],"number":6,"force":81,"legend":false},{"playerId":"josko-gvardiol","name":"Gvardiol","sel":"CRO","copa":2022,"positions":["ZAG","LE"],"number":20,"force":87,"legend":false},{"playerId":"borna-sosa","name":"Sosa","sel":"CRO","copa":2022,"positions":["LE"],"number":19,"force":80,"legend":false},{"playerId":"domagoj-vida","name":"Vida","sel":"CRO","copa":2022,"positions":["ZAG"],"number":21,"force":76,"legend":false},{"playerId":"luka-modric","name":"Modrić","sel":"CRO","copa":2022,"positions":["MC"],"number":10,"force":92,"legend":true},{"playerId":"mateo-kovacic","name":"Kovačić","sel":"CRO","copa":2022,"positions":["MC"],"number":8,"force":87,"legend":false},{"playerId":"marcelo-brozovic","name":"Brozović","sel":"CRO","copa":2022,"positions":["VOL"],"number":11,"force":86,"legend":false},{"playerId":"nikola-vlasic","name":"Vlašić","sel":"CRO","copa":2022,"positions":["MEI","PE","ME"],"number":13,"force":82,"legend":false},{"playerId":"mario-pasalic","name":"Pašalić","sel":"CRO","copa":2022,"positions":["MC"],"number":15,"force":81,"legend":false},{"playerId":"luka-sucic","name":"Sučić","sel":"CRO","copa":2022,"positions":["MC"],"number":25,"force":76,"legend":false},{"playerId":"lovro-majer","name":"Majer","sel":"CRO","copa":2022,"positions":["MEI","PD","MD"],"number":7,"force":80,"legend":false},{"playerId":"ivan-perisic","name":"Perišić","sel":"CRO","copa":2022,"positions":["PE","PD"],"number":4,"force":87,"legend":true},{"playerId":"andrej-kramaric","name":"Kramarić","sel":"CRO","copa":2022,"positions":["CA","MEI"],"number":9,"force":85,"legend":false},{"playerId":"marko-livaja","name":"Livaja","sel":"CRO","copa":2022,"positions":["CA","PE"],"number":14,"force":77,"legend":false},{"playerId":"bruno-petkovic","name":"Petković","sel":"CRO","copa":2022,"positions":["CA"],"number":16,"force":78,"legend":false},{"playerId":"ante-budimir","name":"Budimir","sel":"CRO","copa":2022,"positions":["CA"],"number":17,"force":76,"legend":false},{"playerId":"mislav-orsic","name":"Oršić","sel":"CRO","copa":2022,"positions":["PE","PD"],"number":18,"force":79,"legend":false}]}