{"sel":"RUS","copa":2018,"squad":[{"playerId":"igor-akinfeev","name":"Akinfeev","sel":"RUS","copa":2018,"positions":["GOL"],"number":1,"force":82,"legend":false},{"playerId":"mario-fernandes","name":"Fernandes","sel":"RUS","copa":2018,"positions":["LD","MD"],"number":2,"force":78,"legend":false},{"playerId":"ilya-kutepov","name":"Kutepov","sel":"RUS","copa":2018,"positions":["ZAG"],"number":3,"force":75,"legend":false},{"playerId":"sergei-ignashevich","name":"Ignashevich","sel":"RUS","copa":2018,"positions":["ZAG"],"number":4,"force":77,"legend":false},{"playerId":"andrei-semyonov","name":"Semyonov","sel":"RUS","copa":2018,"positions":["ZAG"],"number":5,"force":71,"legend":false},{"playerId":"denis-cheryshev","name":"Cheryshev","sel":"RUS","copa":2018,"positions":["ME","PE","MEI"],"number":6,"force":80,"legend":false},{"playerId":"daler-kuzyayev","name":"Kuzyayev","sel":"RUS","copa":2018,"positions":["VOL","MC","MD"],"number":7,"force":76,"legend":false},{"playerId":"yury-gazinsky","name":"Gazinsky","sel":"RUS","copa":2018,"positions":["VOL","MD"],"number":8,"force":73,"legend":false},{"playerId":"alan-dzagoev","name":"Dzagoev","sel":"RUS","copa":2018,"positions":["MEI","ME"],"number":9,"force":78,"legend":false},{"playerId":"fyodor-smolov","name":"Smolov","sel":"RUS","copa":2018,"positions":["CA","PE"],"number":10,"force":77,"legend":false},{"playerId":"roman-zobnin","name":"Zobnin","sel":"RUS","copa":2018,"positions":["VOL","MC","MD"],"number":11,"force":76,"legend":false},{"playerId":"andrey-lunyov","name":"Lunyov","sel":"RUS","copa":2018,"positions":["GOL"],"number":12,"force":72,"legend":false},{"playerId":"fyodor-kudryashov","name":"Kudryashov","sel":"RUS","copa":2018,"positions":["LE","ZAG"],"number":13,"force":74,"legend":false},{"playerId":"vladimir-granat","name":"Granat","sel":"RUS","copa":2018,"positions":["ZAG","LE"],"number":14,"force":72,"legend":false},{"playerId":"aleksei-miranchuk","name":"Al. Miranchuk","sel":"RUS","copa":2018,"positions":["MEI","PD"],"number":15,"force":76,"legend":false},{"playerId":"anton-miranchuk","name":"An. Miranchuk","sel":"RUS","copa":2018,"positions":["MC","ME","MEI"],"number":16,"force":71,"legend":false},{"playerId":"aleksandr-golovin","name":"Golovin","sel":"RUS","copa":2018,"positions":["MEI","MD","PD"],"number":17,"force":83,"legend":false},{"playerId":"yuri-zhirkov","name":"Zhirkov","sel":"RUS","copa":2018,"positions":["LE","ME"],"number":18,"force":78,"legend":false},{"playerId":"aleksandr-samedov","name":"Samedov","sel":"RUS","copa":2018,"positions":["PD","MD"],"number":19,"force":74,"legend":false},{"playerId":"vladimir-gabulov","name":"Gabulov","sel":"RUS","copa":2018,"positions":["GOL"],"number":20,"force":70,"legend":false},{"playerId":"aleksandr-yerokhin","name":"Yerokhin","sel":"RUS","copa":2018,"positions":["MC","CA"],"number":21,"force":72,"legend":false},{"playerId":"artem-dzyuba","name":"Dzyuba","sel":"RUS","copa":2018,"positions":["CA","PE"],"number":22,"force":80,"legend":false},{"playerId":"igor-smolnikov","name":"Smolnikov","sel":"RUS","copa":2018,"positions":["LD","MD"],"number":23,"force":74,"legend":false}]}